README.md
setup.cfg
setup.py
tbl7_lib/Binomialdistribution.py
tbl7_lib/Gaussiandistribution.py
tbl7_lib/Generaldistribution.py
tbl7_lib/__init__.py
tbl7_lib.egg-info/PKG-INFO
tbl7_lib.egg-info/SOURCES.txt
tbl7_lib.egg-info/dependency_links.txt
tbl7_lib.egg-info/not-zip-safe
tbl7_lib.egg-info/top_level.txt