Metadata-Version: 2.1
Name: tbl7-lib
Version: 0.0
Summary: initial_own_package
Home-page: UNKNOWN
Author-email: tomblanke1@gmail.com
License: UNKNOWN
Platform: UNKNOWN
